slackarchiver/__init__.py
slackarchiver/cli.py
slackarchiver/manage_channel.py
slackarchiver/settings.py
slackarchiver/utils.py
slack_archiver_cli-1.1.1.dist-info/entry_points.txt
slack_archiver_cli-1.1.1.dist-info/LICENSE
slack_archiver_cli-1.1.1.dist-info/WHEEL
slack_archiver_cli-1.1.1.dist-info/METADATA
slack_archiver_cli-1.1.1.dist-info/RECORD
