Metadata-Version: 2.1
Name: slack-archiver-cli
Version: 1.1.1
Summary: A CLI tool to archive many slack channels at once
Home-page: https://github.com/joe-yama/slack-archiver-cli
License: MIT
Author: joe-yama
Author-email: s1r0mqme@gmail.com
Requires-Python: >=3.8,<4
Classifier: License :: OSI Approved :: MIT License
Classifier: Programming Language :: Python :: 3
Classifier: Programming Language :: Python :: 3.10
Classifier: Programming Language :: Python :: 3.8
Classifier: Programming Language :: Python :: 3.9
Requires-Dist: fire (>=0.4.0,<0.5.0)
Requires-Dist: python-dotenv (>=0.19.2,<0.20.0)
Requires-Dist: slack-sdk (>=3.15.2,<4.0.0)
Project-URL: Repository, https://github.com/joe-yama/slack-archiver-cli
